selfdev/spi_master.v
`timescale 1ps/1ps

module spi_master #(
    parameter DEFAULT_CLK_DIV = 4
)(
    input  wire        clk,
    input  wire        reset,

    // Control interface
    input  wire        start,
    input  wire [7:0]  tx_data,
    input  wire [15:0] clk_div_in,
    output reg  [7:0]  rx_data,
    output reg         ready,
    output reg         busy,
    output reg         done,
    output reg         irq,

    // SPI signals
    input  wire        miso,
    output reg         mosi,
    output reg         sclk,
    output reg         cs
);

    // Internal signals
    reg [7:0]  tx_shift;
    reg [7:0]  rx_shift;
    reg [3:0]  bit_cnt;
    reg [15:0] clk_cnt;
    reg [15:0] clk_div_reg;  // holds active divider
    reg        sclk_en;

    // FSM states
    localparam READY    = 2'b00,
               IDLE     = 2'b01,
               TRANSFER = 2'b10,
               FINISH   = 2'b11;

    reg [1:0] state, next_state;

    // Clock Divider
    always @(posedge clk or posedge reset) begin
        if (reset) begin
            clk_cnt <= 0;
            sclk    <= 0;
        end else if (sclk_en) begin
            if (clk_cnt == (clk_div_reg/2 - 1)) begin
                clk_cnt <= 0;
                sclk    <= ~sclk;
            end else begin
                clk_cnt <= clk_cnt + 1;
            end
        end else begin
            clk_cnt <= 0;
            sclk    <= 0;
        end
    end

    // State machine
    always @(posedge clk or posedge reset) begin
        if (reset) begin
            state       <= READY;
            ready       <= 1;
            busy        <= 0;
            done        <= 0;
            irq         <= 0;
            cs          <= 1;
            mosi        <= 0;
            rx_data     <= 0;
            tx_shift    <= 0;
            rx_shift    <= 0;
            bit_cnt     <= 0;
            sclk_en     <= 0;
            clk_div_reg <= DEFAULT_CLK_DIV;
        end else begin
            state <= next_state;

            // Default: clear interrupt unless asserted in FINISH
            irq <= 0;

            case (state)
                READY: begin
                    ready <= 1;
                    busy  <= 0;
                    done  <= 0;
                    cs    <= 1;
                end

                IDLE: begin
                    ready <= 0;
                    busy  <= 0;
                    done  <= 0;
                    cs    <= 1;
                    sclk_en <= 0;
                    if (start) begin
                        busy        <= 1;
                        cs          <= 0;
                        tx_shift    <= tx_data;
                        rx_shift    <= 0;
                        bit_cnt     <= 8;
                        sclk_en     <= 1;
                        clk_div_reg <= (clk_div_in == 0) ? DEFAULT_CLK_DIV : clk_div_in; 
                    end
                end

                TRANSFER: begin
                    // On falling edge: output data
                    if (sclk == 0 && clk_cnt == 0) begin
                        mosi     <= tx_shift[7];
                        tx_shift <= {tx_shift[6:0], 1'b0};
                    end

                    // On rising edge: sample data
                    if (sclk == 1 && clk_cnt == 0) begin
                        rx_shift <= {rx_shift[6:0], miso};
                        if (bit_cnt > 0)
                            bit_cnt <= bit_cnt - 1;
                    end
                end

                FINISH: begin
                    busy    <= 0;
                    done    <= 1;
                    cs      <= 1;
                    sclk_en <= 0;
                    rx_data <= rx_shift;
                    irq     <= 1; 
                end
            endcase
        end
    end

    // Next-state logic
    always @(*) begin
        next_state = state;
        case (state)
            READY:    next_state = IDLE;
            IDLE:     if (start) next_state = TRANSFER;
            TRANSFER: if (bit_cnt == 0 && sclk == 1 && clk_cnt == 0)
                          next_state = FINISH;
            FINISH:   next_state = READY;
        endcase
    end

endmodule

selfdev/axi_spi_master.v
`timescale 1ps/1ps

module axi_spi_master #(
    parameter DEFAULT_CLK_DIV = 4,
    parameter AXI_ADDR_WIDTH = 32,
    parameter AXI_DATA_WIDTH = 32
)(
    // Clock and Reset
    input  wire                        axi_aclk,
    input  wire                        axi_aresetn,
    
    // AXI4-Lite Write Address Channel
    input  wire [AXI_ADDR_WIDTH-1:0]  s_axi_awaddr,
    input  wire [2:0]                  s_axi_awprot,
    input  wire                        s_axi_awvalid,
    output reg                         s_axi_awready,
    
    // AXI4-Lite Write Data Channel
    input  wire [AXI_DATA_WIDTH-1:0]  s_axi_wdata,
    input  wire [(AXI_DATA_WIDTH/8)-1:0] s_axi_wstrb,
    input  wire                        s_axi_wvalid,
    output reg                         s_axi_wready,
    
    // AXI4-Lite Write Response Channel
    output reg  [1:0]                  s_axi_bresp,
    output reg                         s_axi_bvalid,
    input  wire                        s_axi_bready,
    
    // AXI4-Lite Read Address Channel
    input  wire [AXI_ADDR_WIDTH-1:0]  s_axi_araddr,
    input  wire [2:0]                  s_axi_arprot,
    input  wire                        s_axi_arvalid,
    output reg                         s_axi_arready,
    
    // AXI4-Lite Read Data Channel
    output reg  [AXI_DATA_WIDTH-1:0]  s_axi_rdata,
    output reg  [1:0]                  s_axi_rresp,
    output reg                         s_axi_rvalid,
    input  wire                        s_axi_rready,
    
    // SPI Interface
    input  wire                        miso,
    output wire                        mosi,
    output wire                        sclk,
    output wire                        cs,
    
    // Interrupt
    output wire                        irq_out
);

    // Register Map:
    // 0x00: CONTROL (bit 0: start, bit 1: enable_irq)
    // 0x04: STATUS (bit 0: ready, bit 1: busy, bit 2: done, bit 3: irq_flag)
    // 0x08: TX_DATA
    // 0x0C: RX_DATA
    // 0x10: CLK_DIV
    
    localparam ADDR_CONTROL = 5'h00;
    localparam ADDR_STATUS  = 5'h04;
    localparam ADDR_TX_DATA = 5'h08;
    localparam ADDR_RX_DATA = 5'h0C;
    localparam ADDR_CLK_DIV = 5'h10;
    
    // AXI FSM States
    localparam AXI_WRITE_IDLE = 2'b00;
    localparam AXI_WRITE_DATA = 2'b01;
    localparam AXI_WRITE_RESP = 2'b10;
    
    localparam AXI_READ_IDLE = 2'b00;
    localparam AXI_READ_DATA = 2'b01;
    
    // Internal registers
    reg        control_start;
    reg        control_enable_irq;
    reg [7:0]  tx_data_reg;
    reg [15:0] clk_div_reg;
    reg        irq_flag;
    
    // AXI FSM registers
    reg [1:0] axi_write_state;
    reg [1:0] axi_read_state;
    reg [AXI_ADDR_WIDTH-1:0] write_addr;
    reg [AXI_ADDR_WIDTH-1:0] read_addr;
    
    // SPI core signals
    wire       spi_ready;
    wire       spi_busy;
    wire       spi_done;
    wire       spi_irq;
    wire [7:0] spi_rx_data;
    
    // Reset logic
    wire reset = ~axi_aresetn;
    
    // SPI Master instantiation
    spi_master #(
        .DEFAULT_CLK_DIV(DEFAULT_CLK_DIV)
    ) spi_core (
        .clk        (axi_aclk),
        .reset      (reset),
        .start      (control_start),
        .tx_data    (tx_data_reg),
        .clk_div_in (clk_div_reg),
        .rx_data    (spi_rx_data),
        .ready      (spi_ready),
        .busy       (spi_busy),
        .done       (spi_done),
        .irq        (spi_irq),
        .miso       (miso),
        .mosi       (mosi),
        .sclk       (sclk),
        .cs         (cs)
    );
    
    // Interrupt logic
    always @(posedge axi_aclk or posedge reset) begin
        if (reset) begin
            irq_flag <= 1'b0;
        end else begin
            // Priority to clear over set
            if (axi_write_state == AXI_WRITE_DATA && 
                write_addr[4:0] == ADDR_STATUS && 
                s_axi_wstrb[0] &&  // Only if writing to byte 0
                s_axi_wdata[3] == 1'b0) begin
                // Clear IRQ flag when writing 0 to status[3]
                irq_flag <= 1'b0;
            end else if (spi_irq) begin
                irq_flag <= 1'b1;
            end
        end
    end
    
    assign irq_out = irq_flag & control_enable_irq;
    
    // AXI Write Logic
    always @(posedge axi_aclk or posedge reset) begin
        if (reset) begin
            axi_write_state  <= AXI_WRITE_IDLE;
            s_axi_awready    <= 1'b0;
            s_axi_wready     <= 1'b0;
            s_axi_bvalid     <= 1'b0;
            s_axi_bresp      <= 2'b00;
            write_addr       <= 0;
            control_start    <= 1'b0;
            control_enable_irq <= 1'b0;
            tx_data_reg      <= 8'h00;
            clk_div_reg      <= DEFAULT_CLK_DIV;
        end else begin
            // Auto-clear start bit
            control_start <= 1'b0;
            
            case (axi_write_state)
                AXI_WRITE_IDLE: begin
                    s_axi_bvalid <= 1'b0;
                    s_axi_bresp  <= 2'b00;  // Reset response
                    if (s_axi_awvalid) begin
                        s_axi_awready   <= 1'b1;
                        write_addr      <= s_axi_awaddr;
                        axi_write_state <= AXI_WRITE_DATA;
                    end
                end
                
                AXI_WRITE_DATA: begin
                    s_axi_awready <= 1'b0;
                    if (s_axi_wvalid) begin
                        s_axi_wready <= 1'b1;
                        axi_write_state <= AXI_WRITE_RESP;
                        
                        // Register writes with wstrb handling
                        case (write_addr[4:0])
                            ADDR_CONTROL: begin
                                if (s_axi_wstrb[0]) begin
                                    control_start      <= s_axi_wdata[0];
                                    control_enable_irq <= s_axi_wdata[1];
                                end
                            end
                            ADDR_TX_DATA: begin
                                if (s_axi_wstrb[0]) tx_data_reg <= s_axi_wdata[7:0];
                            end
                            ADDR_CLK_DIV: begin
                                if (!spi_busy) begin // Only allow write when not busy
                                    if (s_axi_wstrb[0]) clk_div_reg[7:0]  <= s_axi_wdata[7:0];
                                    if (s_axi_wstrb[1]) clk_div_reg[15:8] <= s_axi_wdata[15:8];
                                end else begin
                                    s_axi_bresp <= 2'b10; // SLVERR - cannot write while busy
                                end
                            end
                            default: begin
                                s_axi_bresp <= 2'b10; // SLVERR
                            end
                        endcase
                    end
                end
                
                AXI_WRITE_RESP: begin
                    s_axi_wready <= 1'b0;
                    if (!s_axi_bvalid) begin
                        s_axi_bvalid <= 1'b1;
                    end else if (s_axi_bready) begin
                        s_axi_bvalid    <= 1'b0;
                        axi_write_state <= AXI_WRITE_IDLE;
                    end
                end
            endcase
        end
    end
    
    // AXI Read Logic
    always @(posedge axi_aclk or posedge reset) begin
        if (reset) begin
            axi_read_state <= AXI_READ_IDLE;
            s_axi_arready  <= 1'b0;
            s_axi_rvalid   <= 1'b0;
            s_axi_rdata    <= 32'h0;
            s_axi_rresp    <= 2'b00;
            read_addr      <= 0;
        end else begin
            case (axi_read_state)
                AXI_READ_IDLE: begin
                    s_axi_rvalid <= 1'b0;
                    if (s_axi_arvalid) begin
                        s_axi_arready   <= 1'b1;
                        read_addr       <= s_axi_araddr;
                        axi_read_state  <= AXI_READ_DATA;
                    end
                end
                
                AXI_READ_DATA: begin
                    s_axi_arready <= 1'b0;
                    s_axi_rvalid  <= 1'b1;
                    
                    // Default values
                    s_axi_rresp <= 2'b00; // OKAY
                    s_axi_rdata <= 32'h0;
                    
                    // Register reads
                    case (read_addr[4:0])
                        ADDR_CONTROL: begin
                            s_axi_rdata <= {30'h0, control_enable_irq, control_start};
                        end
                        ADDR_STATUS: begin
                            s_axi_rdata <= {28'h0, irq_flag, spi_done, spi_busy, spi_ready};
                        end
                        ADDR_TX_DATA: begin
                            s_axi_rdata <= {24'h0, tx_data_reg};
                        end
                        ADDR_RX_DATA: begin
                            s_axi_rdata <= {24'h0, spi_rx_data};
                        end
                        ADDR_CLK_DIV: begin
                            s_axi_rdata <= {16'h0, clk_div_reg};
                        end
                        default: begin
                            s_axi_rresp <= 2'b10; // SLVERR
                        end
                    endcase
                    
                    if (s_axi_rready) begin
                        s_axi_rvalid   <= 1'b0;
                        axi_read_state <= AXI_READ_IDLE;
                    end
                end
            endcase
        end
    end

endmodule

selfdev/axi_spi_master_tb.v
`timescale 1ns/1ps

module axi_spi_master_tb;

    parameter CLK_PERIOD = 10;
    
    // Signals
    reg         clk;
    reg         resetn;
    reg [31:0]  awaddr;
    reg         awvalid;
    wire        awready;
    reg [31:0]  wdata;
    reg [3:0]   wstrb;
    reg         wvalid;
    wire        wready;
    wire [1:0]  bresp;
    wire        bvalid;
    reg         bready;
    reg [31:0]  araddr;
    reg         arvalid;
    wire        arready;
    wire [31:0] rdata;
    wire [1:0]  rresp;
    wire        rvalid;
    reg         rready;
    reg         miso;
    wire        mosi;
    wire        sclk;
    wire        cs;
    wire        irq;
    
    // DUT
    axi_spi_master dut (
        .axi_aclk(clk),
        .axi_aresetn(resetn),
        .s_axi_awaddr(awaddr),
        .s_axi_awprot(3'b000),
        .s_axi_awvalid(awvalid),
        .s_axi_awready(awready),
        .s_axi_wdata(wdata),
        .s_axi_wstrb(wstrb),
        .s_axi_wvalid(wvalid),
        .s_axi_wready(wready),
        .s_axi_bresp(bresp),
        .s_axi_bvalid(bvalid),
        .s_axi_bready(bready),
        .s_axi_araddr(araddr),
        .s_axi_arprot(3'b000),
        .s_axi_arvalid(arvalid),
        .s_axi_arready(arready),
        .s_axi_rdata(rdata),
        .s_axi_rresp(rresp),
        .s_axi_rvalid(rvalid),
        .s_axi_rready(rready),
        .miso(miso),
        .mosi(mosi),
        .sclk(sclk),
        .cs(cs),
        .irq_out(irq)
    );
    
    // Clock
    always #(CLK_PERIOD/2) clk = ~clk;
    
    // Simple loopback
    always @(posedge sclk) begin
        if (!cs) miso <= mosi;
    end
    
    initial begin
        // Init
        clk = 0;
        resetn = 0;
        awaddr = 0;
        awvalid = 0;
        wdata = 0;
        wstrb = 0;
        wvalid = 0;
        bready = 1;
        araddr = 0;
        arvalid = 0;
        rready = 1;
        miso = 0;
        
        #100 resetn = 1;
        #50;
        
        $display("=== AXI SPI Master Testbench ===");
        
        // Write to TX_DATA (0x08)
        $display("[INFO] Writing TX data: 0x55");
        
        // AXI Write Address Phase
        @(posedge clk);
        awaddr = 32'h08;
        awvalid = 1;
        
        $display("[DEBUG] Waiting for awready...");
        wait(awready);
        @(posedge clk);
        awvalid = 0;
        $display("[DEBUG] Address phase complete");
        
        // AXI Write Data Phase
        wdata = 32'h55;
        wvalid = 1;
        wstrb = 4'hF;
        
        $display("[DEBUG] Waiting for wready...");
        wait(wready);
        @(posedge clk);
        wvalid = 0;
        $display("[DEBUG] Data phase complete");
        
        // AXI Write Response Phase
        $display("[DEBUG] Waiting for bvalid...");
        wait(bvalid);
        @(posedge clk);
        $display("[INFO] TX Data written successfully");
        
        // Start transfer (write to CONTROL 0x00)
        $display("[INFO] Starting SPI transfer");
        
        // Address phase
        @(posedge clk);
        awaddr = 32'h00;
        awvalid = 1;
        wait(awready);
        @(posedge clk);
        awvalid = 0;
        
        // Data phase
        wdata = 32'h01; // start bit
        wvalid = 1;
        wait(wready);
        @(posedge clk);
        wvalid = 0;
        
        // Response phase
        wait(bvalid);
        @(posedge clk);
        $display("[INFO] Transfer started");
        
        // Wait for SPI completion
        $display("[INFO] Waiting for SPI completion...");
        #5000;
        
        // Read status (0x04)
        araddr = 32'h04;
        arvalid = 1;
        
        wait(arready);
        @(posedge clk);
        arvalid = 0;
        
        wait(rvalid);
        $display("[INFO] Status register: 0x%08h", rdata);
        
        // Read RX data (0x0C)
        @(posedge clk);
        araddr = 32'h0C;
        arvalid = 1;
        
        wait(arready);
        @(posedge clk);
        arvalid = 0;
        
        wait(rvalid);
        $display("[INFO] RX Data: 0x%08h", rdata);
        
        if (rdata[7:0] == 8'h55) begin
            $display("[PASS] Loopback test successful!");
        end else begin
            $display("[FAIL] Loopback test failed - expected 0x55, got 0x%02h", rdata[7:0]);
        end
        
        // Test another pattern
        $display("\n=== Testing pattern 0xAA ===");
        
        // Write TX data
        @(posedge clk);
        awaddr = 32'h08;
        awvalid = 1;
        wdata = 32'hAA;
        wvalid = 1;
        wstrb = 4'hF;
        
        wait(awready && wready);
        @(posedge clk);
        awvalid = 0;
        wvalid = 0;
        wait(bvalid);
        
        // Start transfer
        @(posedge clk);
        awaddr = 32'h00;
        awvalid = 1;
        wdata = 32'h01;
        wvalid = 1;
        
        wait(awready && wready);
        @(posedge clk);
        awvalid = 0;
        wvalid = 0;
        wait(bvalid);
        
        // Wait and read result
        #5000;
        
        araddr = 32'h0C;
        arvalid = 1;
        wait(arready);
        @(posedge clk);
        arvalid = 0;
        wait(rvalid);
        
        $display("[INFO] RX Data: 0x%08h", rdata);
        if (rdata[7:0] == 8'hAA) begin
            $display("[PASS] Second test successful!");
        end else begin
            $display("[FAIL] Second test failed");
        end
        
        #1000;
        $display("\n=== Test completed ===");
        $finish;
    end
    
    // Timeout watchdog
    initial begin
        #10000; // Shorter timeout for debugging
        $display("[ERROR] Testbench timeout!");
        $display("[DEBUG] Current signals:");
        $display("  awready = %b", awready);
        $display("  wready = %b", wready);  
        $display("  bvalid = %b", bvalid);
        $display("  arready = %b", arready);
        $display("  rvalid = %b", rvalid);
        $finish;
    end
    
    // Dump waveforms
    initial begin
        $dumpfile("axi_spi_master_tb.vcd");
        $dumpvars(0, axi_spi_master_tb);
    end

endmodule

selfdev/axi_spi_master_tb.vcd
$date
	Sun Sep 21 16:00:57 2025
$end
$version
	Icarus Verilog
$end
$timescale
	1ps
$end
$scope module axi_spi_master_tb $end
$var wire 1 ! wready $end
$var wire 1 " sclk $end
$var wire 1 # rvalid $end
$var wire 2 $ rresp [1:0] $end
$var wire 32 % rdata [31:0] $end
$var wire 1 & mosi $end
$var wire 1 ' irq $end
$var wire 1 ( cs $end
$var wire 1 ) bvalid $end
$var wire 2 * bresp [1:0] $end
$var wire 1 + awready $end
$var wire 1 , arready $end
$var reg 32 - araddr [31:0] $end
$var reg 1 . arvalid $end
$var reg 32 / awaddr [31:0] $end
$var reg 1 0 awvalid $end
$var reg 1 1 bready $end
$var reg 1 2 clk $end
$var reg 1 3 miso $end
$var reg 1 4 resetn $end
$var reg 1 5 rready $end
$var reg 32 6 wdata [31:0] $end
$var reg 4 7 wstrb [3:0] $end
$var reg 1 8 wvalid $end
$scope module dut $end
$var wire 1 2 axi_aclk $end
$var wire 1 4 axi_aresetn $end
$var wire 1 ' irq_out $end
$var wire 1 3 miso $end
$var wire 1 9 reset $end
$var wire 32 : s_axi_araddr [31:0] $end
$var wire 3 ; s_axi_arprot [2:0] $end
$var wire 1 . s_axi_arvalid $end
$var wire 32 < s_axi_awaddr [31:0] $end
$var wire 3 = s_axi_awprot [2:0] $end
$var wire 1 0 s_axi_awvalid $end
$var wire 1 1 s_axi_bready $end
$var wire 1 5 s_axi_rready $end
$var wire 32 > s_axi_wdata [31:0] $end
$var wire 4 ? s_axi_wstrb [3:0] $end
$var wire 1 8 s_axi_wvalid $end
$var wire 8 @ spi_rx_data [7:0] $end
$var wire 1 A spi_ready $end
$var wire 1 B spi_irq $end
$var wire 1 C spi_done $end
$var wire 1 D spi_busy $end
$var wire 1 " sclk $end
$var wire 1 & mosi $end
$var wire 1 ( cs $end
$var reg 2 E axi_read_state [1:0] $end
$var reg 2 F axi_write_state [1:0] $end
$var reg 16 G clk_div_reg [15:0] $end
$var reg 1 H control_enable_irq $end
$var reg 1 I control_start $end
$var reg 1 J irq_flag $end
$var reg 32 K read_addr [31:0] $end
$var reg 1 , s_axi_arready $end
$var reg 1 + s_axi_awready $end
$var reg 2 L s_axi_bresp [1:0] $end
$var reg 1 ) s_axi_bvalid $end
$var reg 32 M s_axi_rdata [31:0] $end
$var reg 2 N s_axi_rresp [1:0] $end
$var reg 1 # s_axi_rvalid $end
$var reg 1 ! s_axi_wready $end
$var reg 8 O tx_data_reg [7:0] $end
$var reg 32 P write_addr [31:0] $end
$scope module spi_core $end
$var wire 1 2 clk $end
$var wire 16 Q clk_div_in [15:0] $end
$var wire 1 3 miso $end
$var wire 1 9 reset $end
$var wire 1 I start $end
$var wire 8 R tx_data [7:0] $end
$var reg 4 S bit_cnt [3:0] $end
$var reg 1 D busy $end
$var reg 16 T clk_cnt [15:0] $end
$var reg 16 U clk_div_reg [15:0] $end
$var reg 1 ( cs $end
$var reg 1 C done $end
$var reg 1 B irq $end
$var reg 1 & mosi $end
$var reg 2 V next_state [1:0] $end
$var reg 1 A ready $end
$var reg 8 W rx_data [7:0] $end
$var reg 8 X rx_shift [7:0] $end
$var reg 1 " sclk $end
$var reg 1 Y sclk_en $end
$var reg 2 Z state [1:0] $end
$var reg 8 [ tx_shift [7:0] $end
$upscope $end
$upscope $end
$upscope $end
$enddefinitions $end
#0
$dumpvars
b0 [
b0 Z
0Y
b0 X
b0 W
b1 V
b100 U
b0 T
b0 S
b0 R
b100 Q
b0 P
b0 O
b0 N
b0 M
b0 L
b0 K
0J
0I
0H
b100 G
b0 F
b0 E
0D
0C
0B
1A
b0 @
b0 ?
b0 >
b0 =
b0 <
b0 ;
b0 :
19
08
b0 7
b0 6
15
04
03
02
11
00
b0 /
0.
b0 -
0,
0+
b0 *
0)
1(
0'
0&
b0 %
b0 $
0#
0"
0!
$end
#5000
12
#10000
02
#15000
12
#20000
02
#25000
12
#30000
02
#35000
12
#40000
02
#45000
12
#50000
02
#55000
12
#60000
02
#65000
12
#70000
02
#75000
12
#80000
02
#85000
12
#90000
02
#95000
12
#100000
09
02
14
#105000
b1 Z
12
#110000
02
#115000
0A
12
#120000
02
#125000
12
#130000
02
#135000
12
#140000
02
#145000
12
#150000
02
#155000
b1 F
b1000 P
1+
10
b1000 /
b1000 <
12
#160000
02
#165000
b1010101 O
b1010101 R
b10 F
1!
0+
b1111 7
b1111 ?
18
b1010101 6
b1010101 >
00
12
#170000
02
#175000
1)
0!
08
12
#180000
02
#185000
b0 F
0)
12
#190000
02
#195000
b1 F
b0 P
1+
10
b0 /
b0 <
12
#200000
02
#205000
b10 V
1I
b10 F
1!
0+
18
b1 6
b1 >
00
12
#210000
02
#215000
1Y
b1000 S
b1010101 [
0(
1D
b10 Z
1)
0!
0I
08
12
#220000
02
#225000
b0 F
0)
b10101010 [
b1 T
12
#230000
02
#235000
1"
b0 T
12
#240000
02
#245000
b111 S
b1 T
12
#250000
02
#255000
0"
b0 T
12
#260000
02
#265000
b1010100 [
1&
b1 T
12
#270000
02
#275000
13
1"
b0 T
12
#280000
02
#285000
b110 S
b1 X
b1 T
12
#290000
02
#295000
0"
b0 T
12
#300000
02
#305000
b10101000 [
0&
b1 T
12
#310000
02
#315000
03
1"
b0 T
12
#320000
02
#325000
b101 S
b10 X
b1 T
12
#330000
02
#335000
0"
b0 T
12
#340000
02
#345000
b1010000 [
1&
b1 T
12
#350000
02
#355000
13
1"
b0 T
12
#360000
02
#365000
b100 S
b101 X
b1 T
12
#370000
02
#375000
0"
b0 T
12
#380000
02
#385000
b10100000 [
0&
b1 T
12
#390000
02
#395000
03
1"
b0 T
12
#400000
02
#405000
b11 S
b1010 X
b1 T
12
#410000
02
#415000
0"
b0 T
12
#420000
02
#425000
b1000000 [
1&
b1 T
12
#430000
02
#435000
13
1"
b0 T
12
#440000
02
#445000
b10 S
b10101 X
b1 T
12
#450000
02
#455000
0"
b0 T
12
#460000
02
#465000
b10000000 [
0&
b1 T
12
#470000
02
#475000
03
1"
b0 T
12
#480000
02
#485000
b1 S
b101010 X
b1 T
12
#490000
02
#495000
0"
b0 T
12
#500000
02
#505000
b0 [
1&
b1 T
12
#510000
02
#515000
13
1"
b0 T
12
#520000
02
#525000
b0 S
b1010101 X
b1 T
12
#530000
02
#535000
0"
b0 T
12
#540000
02
#545000
0&
b1 T
12
#550000
02
#555000
03
b11 V
1"
b0 T
12
#560000
02
#565000
b0 V
b10101010 X
b11 Z
b1 T
12
#570000
02
#575000
b1 V
0"
b0 T
1B
b10101010 @
b10101010 W
0Y
1(
1C
0D
b0 Z
12
#580000
02
#585000
1J
0C
1A
0B
b1 Z
12
#590000
02
#595000
0A
12
