selfdev/spi_master.v
`timescale 1ps/1ps

module spi_master #(
    parameter DEFAULT_CLK_DIV = 4
)(
    input  wire        clk,
    input  wire        reset,

    // Control interface
    input  wire        start,
    input  wire [7:0]  tx_data,
    input  wire [15:0] clk_div_in,
    output reg  [7:0]  rx_data,
    output reg         ready,
    output reg         busy,
    output reg         done,
    output reg         irq,

    // SPI signals
    input  wire        miso,
    output reg         mosi,
    output reg         sclk,
    output reg         cs
);

    // Internal signals
    reg [7:0]  tx_shift;
    reg [7:0]  rx_shift;
    reg [3:0]  bit_cnt;
    reg [15:0] clk_cnt;
    reg [15:0] clk_div_reg;  // holds active divider
    reg        sclk_en;

    // FSM states
    localparam READY    = 2'b00,
               IDLE     = 2'b01,
               TRANSFER = 2'b10,
               FINISH   = 2'b11;

    reg [1:0] state, next_state;

    // Clock Divider
    always @(posedge clk or posedge reset) begin
        if (reset) begin
            clk_cnt <= 0;
            sclk    <= 0;
        end else if (sclk_en) begin
            if (clk_cnt == (clk_div_reg/2 - 1)) begin
                clk_cnt <= 0;
                sclk    <= ~sclk;
            end else begin
                clk_cnt <= clk_cnt + 1;
            end
        end else begin
            clk_cnt <= 0;
            sclk    <= 0;
        end
    end

    // State machine
    always @(posedge clk or posedge reset) begin
        if (reset) begin
            state       <= READY;
            ready       <= 1;
            busy        <= 0;
            done        <= 0;
            irq         <= 0;
            cs          <= 1;
            mosi        <= 0;
            rx_data     <= 0;
            tx_shift    <= 0;
            rx_shift    <= 0;
            bit_cnt     <= 0;
            sclk_en     <= 0;
            clk_div_reg <= DEFAULT_CLK_DIV;
        end else begin
            state <= next_state;

            // Default: clear interrupt unless asserted in FINISH
            irq <= 0;

            case (state)
                READY: begin
                    ready <= 1;
                    busy  <= 0;
                    done  <= 0;
                    cs    <= 1;
                end

                IDLE: begin
                    ready <= 0;
                    busy  <= 0;
                    done  <= 0;
                    cs    <= 1;
                    sclk_en <= 0;
                    if (start) begin
                        busy        <= 1;
                        cs          <= 0;
                        tx_shift    <= tx_data;
                        rx_shift    <= 0;
                        bit_cnt     <= 8;
                        sclk_en     <= 1;
                        clk_div_reg <= (clk_div_in == 0) ? DEFAULT_CLK_DIV : clk_div_in; 
                        $display("[SPI_MASTER] Start received: TX=0x%02h, CLK_DIV=%d", tx_data, clk_div_in);
                    end
                end

                TRANSFER: begin
                    // On falling edge: output data
                    if (sclk == 0 && clk_cnt == 0) begin
                        mosi     <= tx_shift[7];
                        tx_shift <= {tx_shift[6:0], 1'b0};
                    end

                    // On rising edge: sample data
                    if (sclk == 1 && clk_cnt == 0) begin
                        rx_shift <= {rx_shift[6:0], miso};
                        if (bit_cnt > 0)
                            bit_cnt <= bit_cnt - 1;
                    end
                end

                FINISH: begin
                    busy    <= 0;
                    done    <= 1;
                    cs      <= 1;
                    sclk_en <= 0;
                    rx_data <= rx_shift;
                    irq     <= 1; 
                    $display("[SPI_MASTER] Transfer done: RX=0x%02h", rx_shift);
                end
            endcase
        end
    end

    // Next-state logic
    always @(*) begin
        next_state = state;
        case (state)
            READY:    next_state = IDLE;
            IDLE:     if (start) next_state = TRANSFER;
            TRANSFER: if (bit_cnt == 0 && sclk == 1 && clk_cnt == 0)
                          next_state = FINISH;
            FINISH:   next_state = READY;
        endcase
    end

endmodule

selfdev/spi_master_tb.v
`timescale 1ns/1ps

module spi_master_tb;

  reg clk;
  reg reset;
  reg start;
  reg miso;
  reg [7:0] tx_data;
  reg [15:0] clk_div_in;
  wire [7:0] rx_data;
  wire ready, busy, done, irq;
  wire mosi, sclk, cs;

  // DUT instantiation
  spi_master #(
    .DEFAULT_CLK_DIV(4)
  ) dut (
    .clk        (clk),
    .reset      (reset),
    .start      (start),
    .tx_data    (tx_data),
    .clk_div_in (clk_div_in),
    .rx_data    (rx_data),
    .ready      (ready),
    .busy       (busy),
    .done       (done),
    .irq        (irq),
    .miso       (miso),
    .mosi       (mosi),
    .sclk       (sclk),
    .cs         (cs)
  );

  // Clock generator: 100 MHz
  always #5 clk = ~clk;

  // Loopback MISO from MOSI
  always @(negedge sclk) begin
    if (!cs)
      miso <= mosi;
  end

  initial begin
    $dumpfile("spi_master_tb.vcd");
    $dumpvars(0, spi_master_tb);

    // Init
    clk        = 0;
    reset      = 1;
    start      = 0;
    tx_data    = 8'h00;
    clk_div_in = 16'd0;
    miso       = 0;

    #20 reset = 0;

    // Send first byte
    #20;
    tx_data = 8'hA5;
    start   = 1;
    #10 start = 0;

    wait(done);
    $display("Sent: 0x%0h, Received: 0x%0h", tx_data, rx_data);

    if (tx_data == rx_data)
      $display(" Test Passed");
    else
      $display(" Test Failed");

    #50;

    //Other type
    tx_data = 8'h3C;
    start   = 1;
    #10 start = 0;

    wait(done);
    $display("Sent: 0x%0h, Received: 0x%0h", tx_data, rx_data);
        if (tx_data == rx_data)
      $display("Test Passed");
    else
      $display("Test Failed");

    #50;
    $finish;
  end

endmodule

selfdev/spi_master_tb.vcd
$date
	Sat Oct 04 23:00:31 2025
$end
$version
	Icarus Verilog
$end
$timescale
	1ps
$end
$scope module spi_master_tb $end
$var wire 1 ! sclk $end
$var wire 8 " rx_data [7:0] $end
$var wire 1 # ready $end
$var wire 1 $ mosi $end
$var wire 1 % irq $end
$var wire 1 & done $end
$var wire 1 ' cs $end
$var wire 1 ( busy $end
$var reg 1 ) clk $end
$var reg 16 * clk_div_in [15:0] $end
$var reg 1 + miso $end
$var reg 1 , reset $end
$var reg 1 - start $end
$var reg 8 . tx_data [7:0] $end
$scope module dut $end
$var wire 1 ) clk $end
$var wire 16 / clk_div_in [15:0] $end
$var wire 1 + miso $end
$var wire 1 , reset $end
$var wire 1 - start $end
$var wire 8 0 tx_data [7:0] $end
$var reg 4 1 bit_cnt [3:0] $end
$var reg 1 ( busy $end
$var reg 16 2 clk_cnt [15:0] $end
$var reg 16 3 clk_div_reg [15:0] $end
$var reg 1 ' cs $end
$var reg 1 & done $end
$var reg 1 % irq $end
$var reg 1 $ mosi $end
$var reg 2 4 next_state [1:0] $end
$var reg 1 # ready $end
$var reg 8 5 rx_data [7:0] $end
$var reg 8 6 rx_shift [7:0] $end
$var reg 1 ! sclk $end
$var reg 1 7 sclk_en $end
$var reg 2 8 state [1:0] $end
$var reg 8 9 tx_shift [7:0] $end
$upscope $end
$upscope $end
$enddefinitions $end
#0
$dumpvars
b0 9
b0 8
07
b0 6
b0 5
b1 4
b100 3
b0 2
b0 1
b0 0
b0 /
b0 .
0-
1,
0+
b0 *
0)
0(
1'
0&
0%
0$
1#
b0 "
0!
$end
#5000
1)
#10000
0)
#15000
1)
#20000
0)
0,
#25000
b1 8
1)
#30000
0)
#35000
0#
1)
#40000
b10 4
0)
1-
b10100101 .
b10100101 0
#45000
17
b1000 1
b10100101 9
0'
1(
b10 8
1)
#50000
0)
0-
#55000
b1 2
b1001010 9
1$
1)
#60000
0)
#65000
1!
b0 2
1)
#70000
0)
#75000
b1 2
b111 1
1)
#80000
0)
#85000
1+
0!
b0 2
1)
#90000
0)
#95000
b1 2
b10010100 9
0$
1)
#100000
0)
#105000
1!
b0 2
1)
#110000
0)
#115000
b1 2
b110 1
b1 6
1)
#120000
0)
#125000
0+
0!
b0 2
1)
#130000
0)
#135000
b1 2
b101000 9
1$
1)
#140000
0)
#145000
1!
b0 2
1)
#150000
0)
#155000
b1 2
b101 1
b10 6
1)
#160000
0)
#165000
1+
0!
b0 2
1)
#170000
0)
#175000
b1 2
b1010000 9
0$
1)
#180000
0)
#185000
1!
b0 2
1)
#190000
0)
#195000
b1 2
b100 1
b101 6
1)
#200000
0)
#205000
0+
0!
b0 2
1)
#210000
0)
#215000
b1 2
b10100000 9
1)
#220000
0)
#225000
1!
b0 2
1)
#230000
0)
#235000
b1 2
b11 1
b1010 6
1)
#240000
0)
#245000
0!
b0 2
1)
#250000
0)
#255000
b1 2
b1000000 9
1$
1)
#260000
0)
#265000
1!
b0 2
1)
#270000
0)
#275000
b1 2
b10 1
b10100 6
1)
#280000
0)
#285000
1+
0!
b0 2
1)
#290000
0)
#295000
b1 2
b10000000 9
0$
1)
#300000
0)
#305000
1!
b0 2
1)
#310000
0)
#315000
b1 2
b1 1
b101001 6
1)
#320000
0)
#325000
0+
0!
b0 2
1)
#330000
0)
#335000
b1 2
b0 9
1$
1)
#340000
0)
#345000
1!
b0 2
1)
#350000
0)
#355000
b1 2
b0 1
b1010010 6
1)
#360000
0)
#365000
1+
0!
b0 2
1)
#370000
0)
#375000
b1 2
0$
1)
#380000
0)
#385000
b11 4
1!
b0 2
1)
#390000
0)
#395000
b0 4
b1 2
b10100101 6
b11 8
1)
#400000
0)
#405000
b1 4
1%
b10100101 "
b10100101 5
07
1'
1&
0(
b0 8
0!
b0 2
1)
#410000
0)
#415000
0&
1#
0%
b1 8
1)
#420000
0)
#425000
0#
1)
#430000
0)
#435000
1)
#440000
0)
#445000
1)
#450000
0)
#455000
17
b1000 1
b0 6
b111100 9
0'
1(
b10 8
b10 4
1)
1-
b111100 .
b111100 0
#460000
0)
#465000
b1111000 9
b1 2
1)
0-
#470000
0)
#475000
1!
b0 2
1)
#480000
0)
#485000
b111 1
b1 6
b1 2
1)
#490000
0)
#495000
0+
0!
b0 2
1)
#500000
0)
#505000
b11110000 9
b1 2
1)
#510000
0)
#515000
1!
b0 2
1)
#520000
0)
#525000
b110 1
b10 6
b1 2
1)
#530000
0)
#535000
0!
b0 2
1)
#540000
0)
#545000
b11100000 9
1$
b1 2
1)
#550000
0)
#555000
1!
b0 2
1)
#560000
0)
#565000
b101 1
b100 6
b1 2
1)
#570000
0)
#575000
1+
0!
b0 2
1)
#580000
0)
#585000
b11000000 9
b1 2
1)
#590000
0)
#595000
1!
b0 2
1)
#600000
0)
#605000
b100 1
b1001 6
b1 2
1)
#610000
0)
#615000
0!
b0 2
1)
#620000
0)
#625000
b10000000 9
b1 2
1)
#630000
0)
#635000
1!
b0 2
1)
#640000
0)
#645000
b11 1
b10011 6
b1 2
1)
#650000
0)
#655000
0!
b0 2
1)
#660000
0)
#665000
b0 9
b1 2
1)
#670000
0)
#675000
1!
b0 2
1)
#680000
0)
#685000
b10 1
b100111 6
b1 2
1)
#690000
0)
#695000
0!
b0 2
1)
#700000
0)
#705000
0$
b1 2
1)
#710000
0)
#715000
1!
b0 2
1)
#720000
0)
#725000
b1 1
b1001111 6
b1 2
1)
#730000
0)
#735000
0+
0!
b0 2
1)
#740000
0)
#745000
b1 2
1)
#750000
0)
#755000
1!
b0 2
1)
#760000
0)
#765000
b0 1
b10011110 6
b1 2
1)
#770000
0)
#775000
0!
b0 2
1)
#780000
0)
#785000
b1 2
1)
#790000
0)
#795000
b11 4
1!
b0 2
1)
#800000
0)
#805000
b0 4
b111100 6
b11 8
b1 2
1)
#810000
0)
#815000
b1 4
0!
b0 2
1%
b111100 "
b111100 5
07
1'
1&
0(
b0 8
1)
#820000
0)
#825000
0&
1#
0%
b1 8
1)
#830000
0)
#835000
0#
1)
